nextcord/ext/lava/__init__.py
nextcord/ext/lava/client.py
nextcord/ext/lava/datarw.py
nextcord/ext/lava/events.py
nextcord/ext/lava/exceptions.py
nextcord/ext/lava/models.py
nextcord/ext/lava/node.py
nextcord/ext/lava/nodemanager.py
nextcord/ext/lava/playermanager.py
nextcord/ext/lava/stats.py
nextcord/ext/lava/utils.py
nextcord/ext/lava/websocket.py
nextcord_ext_lava-3.1.4.dist-info/LICENSE
nextcord_ext_lava-3.1.4.dist-info/METADATA
nextcord_ext_lava-3.1.4.dist-info/WHEEL
nextcord_ext_lava-3.1.4.dist-info/top_level.txt
nextcord_ext_lava-3.1.4.dist-info/RECORD
